<?xml version="1.0" encoding="utf-8"?>
<!DOCTYPE hibernate-mapping PUBLIC "-//Hibernate/Hibernate Mapping DTD 3.0//EN"
"http://hibernate.sourceforge.net/hibernate-mapping-3.0.dtd">
<!-- 
    Mapping file autogenerated by MyEclipse Persistence Tools
-->
<hibernate-mapping>
    <class name="com.sl.ncreport.bean.Ncinfo" table="NCInfo" >
  
        <id name="id" type="integer">
         	<column name="id" />
            <generator class="native" />
        </id>
        <property name="company" column="company" type="string"></property>
        <property name="pk_glorgbook" column="pk_glorgbook" type="string"></property>
        <property name="dwpk_checktype" column="dwpk_checktype" type="string"></property>
        <property name="bmpk_checktype" column="bmpk_checktype" type="string"></property>
        <property name="hbpk_checktype" column="hbpk_checktype" type="string"></property>
      
        
      
     
    </class>
</hibernate-mapping>
